zcash_service_status/__init__.py
zcash_service_status/blockchain_explorers_health_check.py
zcash_service_status/communities_and_forums_response_time.py
zcash_service_status/communities_and_forums_response_time_lib.py
zcash_service_status/exchanges_health_check.py
zcash_service_status/metrics.py
zcash_service_status_MANAN_MONGA-0.0.1.dist-info/LICENSE
zcash_service_status_MANAN_MONGA-0.0.1.dist-info/METADATA
zcash_service_status_MANAN_MONGA-0.0.1.dist-info/WHEEL
zcash_service_status_MANAN_MONGA-0.0.1.dist-info/top_level.txt
zcash_service_status_MANAN_MONGA-0.0.1.dist-info/RECORD
