Metadata-Version: 2.1
Name: zcash-service-status-MANAN-MONGA
Version: 0.0.1
Summary: Zcash Service Status Library
Home-page: https://github.com/kebab-mai-haddi/zcash_service_status_library/
Author: Manan Monga
Author-email: mananmonga@gmail.com
License: UNKNOWN
Project-URL: Bug Tracker, https://github.com/kebab-mai-haddi/zcash_service_status_library/issues
Platform: UNKNOWN
Classifier: Programming Language :: Python :: 3
Classifier: License :: OSI Approved :: MIT License
Classifier: Operating System :: OS Independent
Requires-Python: >=3.9
